odoo/addons/fieldservice_google_marker_icon_picker/README.rst
odoo/addons/fieldservice_google_marker_icon_picker/__init__.py
odoo/addons/fieldservice_google_marker_icon_picker/__manifest__.py
odoo/addons/fieldservice_google_marker_icon_picker/i18n/es_CL.po
odoo/addons/fieldservice_google_marker_icon_picker/i18n/fieldservice_google_marker_icon_picker.pot
odoo/addons/fieldservice_google_marker_icon_picker/i18n/pt_BR.po
odoo/addons/fieldservice_google_marker_icon_picker/models/__init__.py
odoo/addons/fieldservice_google_marker_icon_picker/models/fsm_stage.py
odoo/addons/fieldservice_google_marker_icon_picker/readme/CONFIGURE.rst
odoo/addons/fieldservice_google_marker_icon_picker/readme/CONTRIBUTORS.rst
odoo/addons/fieldservice_google_marker_icon_picker/readme/CREDITS.rst
odoo/addons/fieldservice_google_marker_icon_picker/readme/DESCRIPTION.rst
odoo/addons/fieldservice_google_marker_icon_picker/readme/INSTALL.rst
odoo/addons/fieldservice_google_marker_icon_picker/readme/USAGE.rst
odoo/addons/fieldservice_google_marker_icon_picker/static/description/icon.png
odoo/addons/fieldservice_google_marker_icon_picker/static/description/index.html
odoo/addons/fieldservice_google_marker_icon_picker/views/fsm_stage.xml
odoo12_addon_fieldservice_google_marker_icon_picker-12.0.1.1.0.dist-info/METADATA
odoo12_addon_fieldservice_google_marker_icon_picker-12.0.1.1.0.dist-info/WHEEL
odoo12_addon_fieldservice_google_marker_icon_picker-12.0.1.1.0.dist-info/top_level.txt
odoo12_addon_fieldservice_google_marker_icon_picker-12.0.1.1.0.dist-info/RECORD
