Metadata-Version: 2.1
Name: odoo12-addon-fieldservice-google-marker-icon-picker
Version: 12.0.1.1.0
Summary: This module displays google marker icon picker based on apply widget on field
Home-page: https://github.com/OCA/field-service
Author: Open Source Integrators, Odoo Community Association (OCA)
Author-email: support@odoo-community.org
License: AGPL-3
Platform: UNKNOWN
Classifier: Programming Language :: Python
Classifier: Framework :: Odoo
Classifier: License :: OSI Approved :: GNU Affero General Public License v3
Classifier: Development Status :: 4 - Beta
Requires-Python: >=3.5
Requires-Dist: odoo12-addon-fieldservice-google-map
Requires-Dist: odoo12-addon-web-widget-google-marker-icon-picker
Requires-Dist: odoo (<12.1dev,>=12.0a)
Requires-Dist: webcolors
